[
  {
    "repo": "IBM-Cloud/terraform-provider-ibm",
    "title": "refactor(share): File share mount target assign none by default for dp2",
    "url": "https://github.com/IBM-Cloud/terraform-provider-ibm/pull/6482",
    "user": "deepakibms",
    "created_at": "2025-09-29T01:06:27+00:00",
    "body": "```\r\n\r\n$ make test-vpc TEST_NAME=TestAccIbmIsShareMountTarget\r\n=== RUN   TestAccIbmIsShareMountTarget\r\n--- PASS: TestAccIbmIsShareMountTarget (222.75s)\r\n=== RUN   TestAccIbmIsShareMountTargetVNISubnet\r\n--- PASS: TestAccIbmIsShareMountTargetVNISubnet (224.84s)\r\n=== RUN   TestAccIbmIsShareMountTargetV..."
  }
]